{
  "distribution_names": {},
  "file_format_version": 7,
  "module_name": "email.policy",
  "modules_used": [
    {
      "filename": "/Library/Frameworks/Python.framework/Versions/3.13/lib/python3.13/re",
      "finding": "absolute",
      "level": 0,
      "module_kind": "py",
      "module_name": "re",
      "reason": "import",
      "source_ref_line": 5
    },
    {
      "filename": null,
      "finding": "absolute",
      "level": 0,
      "module_kind": "built-in",
      "module_name": "sys",
      "reason": "import",
      "source_ref_line": 6
    },
    {
      "filename": "/Library/Frameworks/Python.framework/Versions/3.13/lib/python3.13/email",
      "finding": "absolute",
      "level": 0,
      "module_kind": "py",
      "module_name": "email",
      "reason": "import path parent",
      "source_ref_line": 7
    },
    {
      "filename": "/Library/Frameworks/Python.framework/Versions/3.13/lib/python3.13/email/_policybase.py",
      "finding": "absolute",
      "level": 0,
      "module_kind": "py",
      "module_name": "email._policybase",
      "reason": "import",
      "source_ref_line": 7
    },
    {
      "filename": "/Library/Frameworks/Python.framework/Versions/3.13/lib/python3.13/email",
      "finding": "absolute",
      "level": 0,
      "module_kind": "py",
      "module_name": "email",
      "reason": "import path parent",
      "source_ref_line": 8
    },
    {
      "filename": "/Library/Frameworks/Python.framework/Versions/3.13/lib/python3.13/email/utils.py",
      "finding": "absolute",
      "level": 0,
      "module_kind": "py",
      "module_name": "email.utils",
      "reason": "import",
      "source_ref_line": 8
    },
    {
      "filename": "/Library/Frameworks/Python.framework/Versions/3.13/lib/python3.13/email",
      "finding": "absolute",
      "level": 0,
      "module_kind": "py",
      "module_name": "email",
      "reason": "import path parent",
      "source_ref_line": 9
    },
    {
      "filename": "/Library/Frameworks/Python.framework/Versions/3.13/lib/python3.13/email/headerregistry.py",
      "finding": "absolute",
      "level": 0,
      "module_kind": "py",
      "module_name": "email.headerregistry",
      "reason": "import",
      "source_ref_line": 9
    },
    {
      "filename": "/Library/Frameworks/Python.framework/Versions/3.13/lib/python3.13/email",
      "finding": "absolute",
      "level": 0,
      "module_kind": "py",
      "module_name": "email",
      "reason": "import path parent",
      "source_ref_line": 10
    },
    {
      "filename": "/Library/Frameworks/Python.framework/Versions/3.13/lib/python3.13/email/contentmanager.py",
      "finding": "absolute",
      "level": 0,
      "module_kind": "py",
      "module_name": "email.contentmanager",
      "reason": "import",
      "source_ref_line": 10
    },
    {
      "filename": "/Library/Frameworks/Python.framework/Versions/3.13/lib/python3.13/email",
      "finding": "absolute",
      "level": 0,
      "module_kind": "py",
      "module_name": "email",
      "reason": "import path parent",
      "source_ref_line": 11
    },
    {
      "filename": "/Library/Frameworks/Python.framework/Versions/3.13/lib/python3.13/email/message.py",
      "finding": "absolute",
      "level": 0,
      "module_kind": "py",
      "module_name": "email.message",
      "reason": "import",
      "source_ref_line": 11
    }
  ],
  "timing_infos": [
    [
      1,
      0.04836354099097662,
      5,
      {
        "1": 62,
        "2": 97,
        "3": 12,
        "4": 7,
        "5": 5,
        "6": 3,
        "7": 2,
        "8": 13,
        "9": 3,
        "10": 1,
        "17": 5,
        "20": 1,
        "22": 1,
        "26": 5,
        "45": 2,
        "46": 1,
        "49": 1,
        "54": 1
      }
    ]
  ]
}